shopify_gql_helper/__init__.py
shopify_gql_helper/client.py
shopify_gql_helper/errors.py
shopify_gql_helper/paginate.py
shopify_gql_helper/py.typed
shopify_gql_helper/session.py
shopify_gql_helper/throttle.py
shopify_gql_helper/transport.py
shopify_gql_helper-0.1.3.dist-info/licenses/LICENSE
shopify_gql_helper-0.1.3.dist-info/METADATA
shopify_gql_helper-0.1.3.dist-info/WHEEL
shopify_gql_helper-0.1.3.dist-info/top_level.txt
shopify_gql_helper-0.1.3.dist-info/RECORD
