Metadata-Version: 2.4
Name: shopify-gql-helper
Version: 0.1.3
Summary: Tiny, production-minded helper for the Shopify Admin GraphQL API
Author: Talha
License: MIT
Project-URL: Homepage, https://github.com/tulayha/shopify-gql-helper-py
Project-URL: Repository, https://github.com/tulayha/shopify-gql-helper-py
Project-URL: Documentation, https://github.com/tulayha/shopify-gql-helper-py#readme
Project-URL: Changelog, https://github.com/tulayha/shopify-gql-helper-py/releases
Project-URL: Issues, https://github.com/tulayha/shopify-gql-helper-py/issues
Keywords: shopify,graphql,pagination,throttling,ecommerce
Classifier: Development Status :: 4 - Beta
Classifier: Intended Audience :: Developers
Classifier: License :: OSI Approved :: MIT License
Classifier: Programming Language :: Python :: 3
Classifier: Programming Language :: Python :: 3 :: Only
Classifier: Programming Language :: Python :: 3.10
Classifier: Programming Language :: Python :: 3.11
Classifier: Programming Language :: Python :: 3.12
Classifier: Operating System :: OS Independent
Classifier: Topic :: Software Development :: Libraries :: Python Modules
Classifier: Topic :: Internet :: WWW/HTTP
Classifier: Typing :: Typed
Requires-Python: >=3.10
License-File: LICENSE
Requires-Dist: requests>=2.32.3
Requires-Dist: urllib3<3,>=2.2
Provides-Extra: dev
Requires-Dist: pytest>=7.0.0; extra == "dev"
Requires-Dist: pytest-cov>=4.0.0; extra == "dev"
Requires-Dist: black>=23.0.0; extra == "dev"
Requires-Dist: mypy>=1.0.0; extra == "dev"
Requires-Dist: types-requests>=2.31.0; extra == "dev"
Dynamic: license-file
